{"format":2,"version":"5.1","globals":"6f970bb3fd818c0086bb8745517713d8","files":{"delivery___init___py":{"hash":"af9d0d0de0ea3b71d198bc63f1499a7d","index":{"nums":[1,0,0,0,0,0,0],"html_filename":"delivery___init___py.html","relative_filename":"delivery/__init__.py"}},"delivery_app_py":{"hash":"efe48b5ea068557bc7d093ea9e3f8a84","index":{"nums":[1,6,0,0,0,0,0],"html_filename":"delivery_app_py.html","relative_filename":"delivery/app.py"}},"delivery___main___py":{"hash":"341e16b343940b4fb45dc12cd418a383","index":{"nums":[1,1,0,1,0,0,0],"html_filename":"delivery___main___py.html","relative_filename":"delivery/__main__.py"}},"delivery_ext___init___py":{"hash":"af9d0d0de0ea3b71d198bc63f1499a7d","index":{"nums":[1,0,0,0,0,0,0],"html_filename":"delivery_ext___init___py.html","relative_filename":"delivery/ext/__init__.py"}},"delivery_ext_api___init___py":{"hash":"8f59a7e9210db62370cd600c1c607645","index":{"nums":[1,0,0,0,0,0,0],"html_filename":"delivery_ext_api___init___py.html","relative_filename":"delivery/ext/api/__init__.py"}},"delivery_ext_site___init___py":{"hash":"b921b4c6aa9ed436fec6d22cbdedb0bb","index":{"nums":[1,3,0,0,0,0,0],"html_filename":"delivery_ext_site___init___py.html","relative_filename":"delivery/ext/site/__init__.py"}},"delivery_ext_site_main_py":{"hash":"09a74e06269652f5cfe5f686a6f6001b","index":{"nums":[1,6,0,1,0,0,0],"html_filename":"delivery_ext_site_main_py.html","relative_filename":"delivery/ext/site/main.py"}}}}